tempailab.py
tempailab-0.0.7.dist-info/LICENSE
tempailab-0.0.7.dist-info/METADATA
tempailab-0.0.7.dist-info/WHEEL
tempailab-0.0.7.dist-info/top_level.txt
tempailab-0.0.7.dist-info/RECORD
