Metadata-Version: 2.1
Name: tempailab
Version: 0.0.7
Summary: artificial intelligence and DBMS lab programs definitions
Home-page: https://github.com/aiml5thsem/tempailab
Author: aiml department
Author-email: aiml5thsem@gmail.com
License: MIT
Keywords: artificial intelligence lab,DBMS lab,aimllab module
Classifier: Programming Language :: Python :: 3
Classifier: License :: OSI Approved :: MIT License
Classifier: Operating System :: OS Independent
Requires-Python: >=3.7
License-File: LICENSE
Requires-Dist: numpy
